{
  "zone": "crest_zone2",
  "mood": "Crest",
  "zone_number": 2,
  "name": "Warm",
  "description": "Add9 \u2014 Coldplay, Maroon 5, OneRepublic",
  "mode": "major",
  "extension_range": [
    0,
    1
  ],
  "chordonomicon_songs": 78375,
  "transitions": {
    "IV": {
      "I": 0.6795,
      "V": 0.1621,
      "ii": 0.0624,
      "IV": 0.0539,
      "vi": 0.0337
    },
    "I": {
      "IV": 0.2802,
      "V": 0.2653,
      "I": 0.2101,
      "ii": 0.1549,
      "vi": 0.0515,
      "iii": 0.0304
    },
    "iii": {
      "I": 0.4299,
      "ii": 0.2196,
      "vi": 0.1164,
      "V": 0.1045,
      "IV": 0.0805,
      "vii": 0.0296,
      "iii": 0.0195
    },
    "vi": {
      "I": 0.2927,
      "IV": 0.2768,
      "V": 0.188,
      "ii": 0.1555,
      "iii": 0.0441,
      "vi": 0.0284
    },
    "V": {
      "I": 0.5594,
      "ii": 0.14,
      "IV": 0.1387,
      "vi": 0.0757,
      "iii": 0.0379,
      "V": 0.0367
    },
    "ii": {
      "I": 0.4662,
      "V": 0.233,
      "IV": 0.1225,
      "iii": 0.0865,
      "vi": 0.0506,
      "ii": 0.0308
    },
    "vii": {
      "I": 0.4373,
      "iii": 0.2916,
      "vi": 0.0777,
      "vii": 0.0732,
      "V": 0.054,
      "ii": 0.0467,
      "IV": 0.0196
    }
  }
}